iftpy/__init__.py
iftpy-0.0.1.dist-info/LICENSE
iftpy-0.0.1.dist-info/METADATA
iftpy-0.0.1.dist-info/WHEEL
iftpy-0.0.1.dist-info/top_level.txt
iftpy-0.0.1.dist-info/RECORD
