Metadata-Version: 2.1
Name: iftpy
Version: 0.0.1
Summary: Read and write infinity editor iftp file
Home-page: https://gitee.com/oxygendioxide/iftpy
Author: oxygen dioxide
Author-email: 1463567152@qq.com
License: Mulan
Platform: UNKNOWN
Classifier: License :: Other/Proprietary License
Classifier: Programming Language :: Python
Classifier: Programming Language :: Python :: 3
Classifier: Programming Language :: Python :: 3.8
Classifier: Programming Language :: Python :: 3.7
Classifier: Programming Language :: Python :: 3.6
Classifier: Programming Language :: Python :: 3.5
Classifier: Topic :: Multimedia :: Sound/Audio :: MIDI
Classifier: Topic :: Multimedia :: Sound/Audio :: Sound Synthesis
Classifier: Programming Language :: Python :: Implementation :: CPython
Requires-Python: >=3.5.0
Provides-Extra: export_dv
Requires-Dist: dvfile ; extra == 'export_dv'
Provides-Extra: export_midi
Requires-Dist: mido ; extra == 'export_midi'
Provides-Extra: export_sheet
Requires-Dist: music21 ; extra == 'export_sheet'
Requires-Dist: utaufile ; extra == 'export_sheet'
Provides-Extra: export_ust
Requires-Dist: utaufile ; extra == 'export_ust'
